{
  "project_info": {
    "project_number": "398628262714",
    "project_id": "firebase-test-tsa"
},
  "client": [
{
  "client_info": {
    "mobilesdk_app_id": "1:398628262714:android:9785bbdd246da20e",
    "android_client_info": {
      "package_name": "com.dozuki.ifixit"
}
},
  "oauth_client": [
{
  "client_id": "398628262714-91fpel9alg2q22srpv4s362m3ttmdh1r.apps.googleusercontent.com",
  "client_type": 3
}
],
  "api_key": [
{
  "current_key": "AIzaSyDrDtCmGeHhOPGuVv2J-UBJOFIzGhPYw8w"
}
],
  "services": {
    "analytics_service": {
      "status": 1
},
    "appinvite_service": {
      "status": 1,
      "other_platform_oauth_client": []
},
    "ads_service": {
      "status": 1
}
}
}
],
  "configuration_version": "1"
}